README.md
setup.cfg
setup.py
gnucash_importer/__init__.py
gnucash_importer/account.py
gnucash_importer/cli.py
gnucash_importer/ledger.py
gnucash_importer/ncurses.py
gnucash_importer/read_entry.py
gnucash_importer/run_app.py
gnucash_importer/util.py
gnucash_importer/version.py
gnucash_magical_importer.egg-info/PKG-INFO
gnucash_magical_importer.egg-info/SOURCES.txt
gnucash_magical_importer.egg-info/dependency_links.txt
gnucash_magical_importer.egg-info/top_level.txt
gnucash_magical_importer.egg-info/version.txt
test/__init__.py
test/test_account.py
test/test_ledger.py
test/test_read_entry.py