Metadata-Version: 2.1
Name: gnucash-magical-importer
Version: 0.1.0
Summary: Parse data source (ofx, qif, csv, etc.) and import to Gnucash file.
Home-page: https://github.com/foguinhoperuca/gnucash_magical_importer
Author: Jefferson Campos
Author-email: jefferson@jeffersoncampos.eti.br
License: UNKNOWN
Platform: UNKNOWN
Classifier: Development Status :: 3 - Alpha
Classifier: Programming Language :: Python :: 3
Classifier: License :: OSI Approved :: GNU General Public License v3 (GPLv3)
Classifier: Operating System :: OS Independent
Requires-Python: >=3.6
